piptree/__init__.py
piptree/tree.py
piptree-0.1.4.data/scripts/piptree
piptree-0.1.4.dist-info/METADATA
piptree-0.1.4.dist-info/WHEEL
piptree-0.1.4.dist-info/top_level.txt
piptree-0.1.4.dist-info/RECORD
